cmtkgen-0.9.data/scripts/cmtkgen
cmtkgen_lib/__init__.py
cmtkgen_lib/cpp_project.py
cmtkgen_lib/create_cpp_executable_project.py
cmtkgen_lib/create_cpp_hello_world.py
cmtkgen_lib/create_cpp_honly_lib_project.py
cmtkgen_lib/create_cpp_lib_project.py
cmtkgen-0.9.dist-info/LICENSE.md
cmtkgen-0.9.dist-info/METADATA
cmtkgen-0.9.dist-info/WHEEL
cmtkgen-0.9.dist-info/top_level.txt
cmtkgen-0.9.dist-info/RECORD
