Metadata-Version: 2.1
Name: cmtkgen
Version: 0.9
Summary: A C++ CMake project generator (using CMake ToolKit)
Home-page: https://github.com/arapelle/cmtkgen
Author: Aymeric Pellé
Author-email: aympelle@gmail.com
License: UNKNOWN
Platform: UNKNOWN
Classifier: Programming Language :: Python :: 3
Classifier: License :: OSI Approved :: MIT License
Classifier: Operating System :: OS Independent
Requires-Python: >=3.6
